fhe.cpython-311-aarch64-linux-gnu.so
libfhe.libs/libgmp-f1995f80.so.10.3.2
libfhe.libs/libfhe-9dca3814.so
libfhe-0.0.1.dist-info/top_level.txt
libfhe-0.0.1.dist-info/METADATA
libfhe-0.0.1.dist-info/WHEEL
libfhe-0.0.1.dist-info/RECORD
