Metadata-Version: 2.1
Name: libfhe
Version: 0.0.1
Summary: Python wrapper for libfhe
Home-page: https://libfhe.org
Author: azzaoui
Author-email: taha@azzaoui.org
Keywords: cryptography,fhe,Homomorphic Encryption
Classifier: Programming Language :: Python :: 3
Classifier: License :: OSI Approved :: GNU General Public License v3 (GPLv3)
Classifier: Topic :: Security :: Cryptography
Classifier: Operating System :: Unix
Classifier: Operating System :: MacOS
Requires-Python: >=3.11
Requires-Dist: Cython
Requires-Dist: gmpy2
Requires-Dist: numpy
Requires-Dist: pytest
